[
  {
    "runId": "28207521169",
    "runNumber": 1276,
    "instance": "top-url-dev22-sso",
    "mode": "periodic",
    "dryRun": false,
    "startedAt": "2026-06-25T23:42:38.140Z",
    "finishedAt": "2026-06-25T23:43:39.568Z",
    "durationMs": 61428,
    "stepsOk": 12,
    "stepsTotal": 16,
    "kpis": {
      "deleted": 0,
      "deferred": 0,
      "deletedOver30d": 0,
      "deleted15to30d": 0,
      "deleted7to15d": 0,
      "restored": 0,
      "created": 245,
      "failed": 0,
      "capHit": 0,
      "localized": 150,
      "already": 0,
      "localizeFailed": 0,
      "localeTargets": 5,
      "published": 50,
      "unpublished": 0,
      "publishFailed": 0,
      "transitioned": 0,
      "transitionFailed": 0,
      "casesOk": 1,
      "casesFailed": 5,
      "churnLocale": 1,
      "branchesCreated": 0,
      "branchEntries": 0,
      "branchLocalized": 0,
      "dynCtCreated": 0,
      "dynCtEntries": 0,
      "workflowBranchAdds": 0,
      "secondWaveEntries": 0,
      "transitions": 0,
      "publishRules": 0,
      "branchesDeleted": 0,
      "ctsDeleted": 0,
      "editedPostPublish": 50,
      "ctCreated": 0,
      "entriesCreated": 0,
      "branchCreated": 0,
      "entriesOnBranch": 0,
      "localizedEntries": 0,
      "branchDeleted": 0,
      "localeDeleted": 0
    },
    "steps": [
      {
        "name": "ensure content types",
        "ok": true,
        "ms": 1708,
        "planned": null,
        "actual": null,
        "failed": 0,
        "kpis": {},
        "errors": []
      },
      {
        "name": "delete old entries",
        "ok": true,
        "ms": 1732,
        "planned": 0,
        "actual": 0,
        "failed": 0,
        "kpis": {
          "deleted": 0,
          "deferred": 0,
          "deletedOver30d": 0,
          "deleted15to30d": 0,
          "deleted7to15d": 0
        },
        "errors": []
      },
      {
        "name": "backfill aged entries",
        "ok": true,
        "ms": 907,
        "planned": 0,
        "actual": 0,
        "failed": 0,
        "kpis": {
          "restored": 0,
          "bands": {
            ">30d": {
              "restored": 0,
              "available": 0
            },
            "15-30d": {
              "restored": 0,
              "available": 0
            },
            "7-15d": {
              "restored": 0,
              "available": 0
            }
          }
        },
        "errors": []
      },
      {
        "name": "periodic entries from manifest",
        "ok": true,
        "ms": 3079,
        "planned": 100,
        "actual": 100,
        "failed": 0,
        "kpis": {
          "created": 100,
          "failed": 0,
          "capHit": 0
        },
        "errors": []
      },
      {
        "name": "localize entries",
        "ok": true,
        "ms": 8012,
        "planned": 150,
        "actual": 150,
        "failed": 0,
        "kpis": {
          "localized": 150,
          "already": 0,
          "localizeFailed": 0,
          "localeTargets": 5
        },
        "errors": []
      },
      {
        "name": "bulk publish cycle",
        "ok": true,
        "ms": 2733,
        "planned": 0,
        "actual": 0,
        "failed": 0,
        "kpis": {
          "published": 0,
          "unpublished": 0,
          "publishFailed": 0,
          "transitioned": 0,
          "transitionFailed": 0
        },
        "errors": []
      },
      {
        "name": "workflow transitions on existing entries",
        "ok": true,
        "ms": 469,
        "planned": null,
        "actual": null,
        "failed": 0,
        "kpis": {},
        "errors": []
      },
      {
        "name": "churn orphan cases",
        "ok": true,
        "ms": 3296,
        "planned": 6,
        "actual": 1,
        "failed": 5,
        "kpis": {
          "casesOk": 1,
          "casesFailed": 5,
          "churnLocale": 1
        },
        "errors": [
          {
            "label": "disable→enable",
            "message": "Churn $all 260619174319 (off 422, on 422)"
          },
          {
            "label": "detach→reattach CT",
            "message": "Quick Publish ⟂ demo_blocks (detach 422, reattach 422)"
          },
          {
            "label": "branch create→delete",
            "message": "create 401"
          },
          {
            "label": "$all workflow create→delete",
            "message": "create 422: Workflow creation failed. Please try again"
          },
          {
            "label": "entry delete→restore",
            "message": "demo_plain_text/blt52a7dae8da439ad3 (delete 200, restore 422)"
          }
        ]
      },
      {
        "name": "branch lifecycle",
        "ok": true,
        "ms": 471,
        "planned": 30,
        "actual": 0,
        "failed": 1,
        "kpis": {
          "branchesCreated": 0,
          "branchEntries": 0,
          "branchLocalized": 0,
          "dynCtCreated": 0,
          "dynCtEntries": 0,
          "workflowBranchAdds": 0,
          "secondWaveEntries": 0,
          "transitions": 0,
          "published": 0,
          "unpublished": 0,
          "publishRules": 0,
          "branchesDeleted": 0,
          "ctsDeleted": 0
        },
        "errors": []
      },
      {
        "name": "edit after publish (entries_in_progress)",
        "ok": true,
        "ms": 19341,
        "planned": 50,
        "actual": 50,
        "failed": 0,
        "kpis": {
          "created": 50,
          "published": 50,
          "editedPostPublish": 50,
          "failed": 0
        },
        "errors": []
      },
      {
        "name": "permanent deletes (entries_deleted)",
        "ok": true,
        "ms": 14484,
        "planned": 75,
        "actual": 75,
        "failed": 0,
        "kpis": {
          "created": 75,
          "deleted": 0,
          "failed": 0
        },
        "errors": []
      },
      {
        "name": "aged stalls (stalled_by_stage)",
        "ok": true,
        "ms": 3752,
        "planned": 20,
        "actual": 20,
        "failed": 0,
        "kpis": {
          "created": 20,
          "transitioned": 0,
          "stalledAtStage": {},
          "failed": 0
        },
        "errors": []
      },
      {
        "name": "no-workflow CT (entries_without_workflow)",
        "ok": false,
        "ms": 357,
        "planned": 25,
        "actual": 0,
        "failed": 1,
        "kpis": {
          "ctCreated": 0,
          "entriesCreated": 0
        },
        "errors": []
      },
      {
        "name": "multi-actor create/publish (user_uid)",
        "ok": false,
        "ms": 363,
        "planned": 10,
        "actual": 0,
        "failed": 1,
        "kpis": {},
        "errors": []
      },
      {
        "name": "branch/locale deletion (orphan cleanup)",
        "ok": false,
        "ms": 376,
        "planned": 15,
        "actual": 0,
        "failed": 1,
        "kpis": {
          "branchCreated": 0,
          "entriesOnBranch": 0,
          "localizedEntries": 0,
          "branchDeleted": 0,
          "localeDeleted": 0,
          "failed": 0
        },
        "errors": []
      },
      {
        "name": "invite 10 users",
        "ok": false,
        "ms": 340,
        "planned": null,
        "actual": null,
        "failed": 0,
        "kpis": {},
        "errors": []
      }
    ],
    "errors": [
      {
        "step": "churn orphan cases",
        "label": "disable→enable",
        "message": "Churn $all 260619174319 (off 422, on 422)"
      },
      {
        "step": "churn orphan cases",
        "label": "detach→reattach CT",
        "message": "Quick Publish ⟂ demo_blocks (detach 422, reattach 422)"
      },
      {
        "step": "churn orphan cases",
        "label": "branch create→delete",
        "message": "create 401"
      },
      {
        "step": "churn orphan cases",
        "label": "$all workflow create→delete",
        "message": "create 422: Workflow creation failed. Please try again"
      },
      {
        "step": "churn orphan cases",
        "label": "entry delete→restore",
        "message": "demo_plain_text/blt52a7dae8da439ad3 (delete 200, restore 422)"
      },
      {
        "step": "no-workflow CT (entries_without_workflow)",
        "label": null,
        "message": "step exited non-zero"
      },
      {
        "step": "multi-actor create/publish (user_uid)",
        "label": null,
        "message": "step exited non-zero"
      },
      {
        "step": "branch/locale deletion (orphan cleanup)",
        "label": null,
        "message": "step exited non-zero"
      },
      {
        "step": "invite 10 users",
        "label": null,
        "message": "step exited non-zero"
      }
    ]
  }
]